autoholidays/__init__.py
autoholidays/_config/__init__.py
autoholidays/_libs/__init__.py
autoholidays/_testing/__init__.py
autoholidays/_testing/run_tests.py
autoholidays/api/__init__.py
autoholidays/core/__init__.py
autoholidays/errors/__init__.py
autoholidays/errors/errors.py
autoholidays/errors/warnings.py
autoholidays-0.0.1.dev0.dist-info/LICENSE
autoholidays-0.0.1.dev0.dist-info/METADATA
autoholidays-0.0.1.dev0.dist-info/WHEEL
autoholidays-0.0.1.dev0.dist-info/top_level.txt
autoholidays-0.0.1.dev0.dist-info/RECORD
