Metadata-Version: 2.1
Name: autoholidays
Version: 0.0.1.dev0
Summary: Create an Optimal Holiday Planner
Author: Debmalya Pramanik
Author-email: 
Classifier: Programming Language :: Python :: 3
Requires-Python: >=3.10
License-File: LICENSE
